{
    "fields":[
        {
            "text":"frequency",
            "label":"Frequency",
            "type":"text",
            "defaultValue":"once"
        },
        {
            "text": "send",
            "label": "Send message to user",
            "type": "switch",
            "defaultValue": false
        },
        {
            "text": "message",
            "label": "Message",
            "hint": "Send escalation message to user",
            "type": "textarea",
            "defaultValue": "Dear {user}, you have a ticket {ticket} in Scheduled On Site coming up. Do you need to leave the office now?"
        },
        {
            "text": "sendEscalation",
            "label": "Send escalation message to user",
            "type": "switch",
            "defaultValue": false
        },
        {
            "text": "times",
            "label": "Escalation trigger times",
            "type": "text",
            "hint": "Escalation trigger times",
            "defaultValue": "3,6,9"
        }
    ]
}


